NeonLightEffect/AddLine.py
NeonLightEffect/GetLines.py
NeonLightEffect/Inner_glow.py
NeonLightEffect/Outer_glow.py
NeonLightEffect/PyPS.py
NeonLightEffect/__init__.py
NeonLightEffect-0.0.4.dist-info/METADATA
NeonLightEffect-0.0.4.dist-info/WHEEL
NeonLightEffect-0.0.4.dist-info/top_level.txt
NeonLightEffect-0.0.4.dist-info/RECORD
